Workbook

Sheet Assumptions
A1: TCO Analysis – Printer Comparison | BRG-ISEA Lab 2a
A3: ASSUMPTIONS & SCENARIO SETUP
A4: Parameter | B4: Value | C4: Unit | D4: Notes
A5: Comparison Period | B5: 5 | C5: years | D5: How long we evaluate costs
A6: Pages Printed per Week | B6: 750 | C6: pages | D6: Lab default assumption
A7: Power On per Week | B7: 40 | C7: hours | D7: Lab default assumption
A8: Electricity Cost | B8: 0.3 | C8: $/kWh | D8: Singapore average ~SGD 0.30
A9: Reams of Paper (500 pg) | B9: =B5 -> 5 | C9: $/ream | D9: Officeworks / local estimate
A10: Weeks per Year | B10: =B9 -> 5 | C10: weeks | D10: Fixed calendar constant
A12: DERIVED VALUES
A13: Derived Metric | B13: Formula | C13: Value
A14: Total Weeks in Period | B14: =B5*52 -> 260 | C14: weeks
A15: Total Pages Printed | B15: =B6*B14 -> 195000 | C15: pages
A17: PRINTER MODELS CHOSEN
A18: Printer | B18: Brand & Model | C18: Type | D18: Category
A19: Printer A | B19: HP DeskJet 2755e | C19: Inkjet | D19: Budget home/small office inkjet
A20: Printer B | B20: Brother HL-L2350DW | C20: Laser | D20: Entry-level office mono laser

Sheet Printer A - Inkjet
A1: Printer A – HP DeskJet 2755e (Inkjet) | TCO Over 5 Years
A3: Item Description | B3: Type (Fixed/Var) | C3: Unit Price (SGD) | D3: Units Consumed | E3: Total Cost (SGD) | F3: Source / Notes
A4: Printer Purchase (HP DeskJet 2755e) | B4: Fixed | C4: 79 | D4: 1 | E4: =C4*D4 -> 79 | F4: Officeworks / Amazon SG
A5: Black Ink Cartridge (HP 65 Black, ~120 pg yield) | B5: Variable | C5: 18 | D5: =Assumptions!B15/120 -> 1625 | E5: =C5*D5 -> 29250 | F5: HP spec sheet; 120 pages/cartridge
A6: Colour Ink Cartridge (HP 65 Colour, ~100 pg yield) | B6: Variable | C6: 22 | D6: =Assumptions!B15/100 -> 1950 | E6: =C6*D6 -> 42900 | F6: HP spec sheet; 100 pages/cartridge (blended)
A7: Paper (Reams of 500 sheets) | B7: Variable | C7: 6 | D7: =Assumptions!B15/500 -> 390 | E7: =C7*D7 -> 2340 | F7: Local office supply; $6/ream
A8: Electricity (Printer ~15W, 40 hrs/wk) | B8: Variable | C8: 0.3 | D8: =0.015*Assumptions!B14*40 -> 156 | E8: =C8*D8 -> 46.8 | F8: 15W × 40 hrs × 260 weeks × $0.30/kWh
A9: Maintenance / Head Cleaning Kit | B9: Variable | C9: 15 | D9: =Assumptions!B5 -> 5 | E9: =C9*D9 -> 75 | F9: ~$15/year estimate
A10: Replacement Printer (end of life ~3 yrs) | B10: Fixed | C10: 79 | D10: 1 | E10: =C10*D10 -> 79 | F10: Inkjet avg lifespan ~3 yrs; 1 replacement over 5 yr
A11: TOTAL COST OF OWNERSHIP – Printer A (Inkjet) | E11: =SUM(E4:E10) -> 74769.8

Sheet Printer B - Laser
A1: Printer B – Brother HL-L2350DW (Laser) | TCO Over 5 Years
A3: Item Description | B3: Type (Fixed/Var) | C3: Unit Price (SGD) | D3: Units Consumed | E3: Total Cost (SGD) | F3: Source / Notes
A4: Printer Purchase (Brother HL-L2350DW) | B4: Fixed | C4: 189 | D4: 1 | E4: =C4*D4 -> 189 | F4: Officeworks / Amazon SG
A5: Toner Cartridge (TN-2450, ~3,000 pg yield) | B5: Variable | C5: 48 | D5: =Assumptions!B15/3000 -> 65 | E5: =C5*D5 -> 3120 | F5: Brother spec; 3000 pages/cartridge
A6: Drum Unit (DR-2425, ~12,000 pg) | B6: Variable | C6: 75 | D6: =Assumptions!B15/12000 -> 16.25 | E6: =C6*D6 -> 1218.75 | F6: Brother spec; 12000 pages/drum
A7: Paper (Reams of 500 sheets) | B7: Variable | C7: 6 | D7: =Assumptions!B15/500 -> 390 | E7: =C7*D7 -> 2340 | F7: Local office supply; $6/ream
A8: Electricity (Laser ~400W active, 40 hrs/wk) | B8: Variable | C8: 0.3 | D8: =0.4*Assumptions!B14*40 -> 4160 | E8: =C8*D8 -> 1248 | F8: 400W × 40 hrs × 260 weeks × $0.30/kWh
A9: Maintenance / Service | B9: Variable | C9: 20 | D9: =Assumptions!B5 -> 5 | E9: =C9*D9 -> 100 | F9: ~$20/year estimate
A10: TOTAL COST OF OWNERSHIP – Printer B (Laser) | E10: =SUM(E4:E9) -> 8215.75

Sheet Comparison Summary
A1: TCO Comparison Summary – Inkjet vs Laser (5-Year Analysis)
A3: COST SUMMARY
A4: Metric | B4: Printer A (Inkjet) | C4: Printer B (Laser) | D4: Difference (A−B) | E4: Better Option
A5: Total 5-Year TCO (SGD) | B5: ='Printer A - Inkjet'!E11 -> 74769.8 | C5: ='Printer B - Laser'!E10 -> 8215.75 | D5: =B5-C5 -> 66554.05 | E5: =IF(B5<C5,"Inkjet ✓","Laser ✓") -> Laser ✓
A6: Total Pages Printed | B6: =Assumptions!B15 -> 195000 | C6: =Assumptions!B15 -> 195000 | D6: - | E6: -
A7: Cost per Page (SGD) | B7: =B5/Assumptions!B15 -> 0.38343487 | C7: =C5/Assumptions!B15 -> 0.042132051 | D7: =B6-C6 -> 0 | E7: =IF(B6<C6,"Inkjet ✓","Laser ✓") -> Laser ✓
A8: Printer Purchase Cost | B8: =79+79 -> 158 | C8: =189 -> 189 | D8: =B7-C7 -> 0.34130282 | E8: =IF(B7<C7,"Inkjet ✓","Laser ✓") -> Laser ✓
A10: 3-YEAR COST PROJECTION
A11: Year | B11: Inkjet Cumul. | C11: Laser Cumul. | D11: Inkjet Annual | E11: Laser Annual
A12: Year 1 | B12: =D12*1 -> 14953.96 | C12: =E12*1 -> 1643.15 | D12: ='Printer A - Inkjet'!E11/5 -> 14953.96 | E12: ='Printer B - Laser'!E10/5 -> 1643.15
A13: Year 2 | B13: =D12*2 -> 29907.92 | C13: =E12*2 -> 3286.3 | D13: ='Printer A - Inkjet'!E11/5 -> 14953.96 | E13: ='Printer B - Laser'!E10/5 -> 1643.15
A14: Year 3 | B14: =D12*3 -> 44861.88 | C14: =E12*3 -> 4929.45 | D14: ='Printer A - Inkjet'!E11/5 -> 14953.96 | E14: ='Printer B - Laser'!E10/5 -> 1643.15
A15: Year 4 | B15: =D12*4 -> 59815.84 | C15: =E12*4 -> 6572.6 | D15: ='Printer A - Inkjet'!E11/5 -> 14953.96 | E15: ='Printer B - Laser'!E10/5 -> 1643.15
A16: Year 5 | B16: =D12*5 -> 74769.8 | C16: =E12*5 -> 8215.75 | D16: ='Printer A - Inkjet'!E11/5 -> 14953.96 | E16: ='Printer B - Laser'!E10/5 -> 1643.15
A19: REFLECTION QUESTIONS
A20: Q# | B20: Question | C20: Answer
A21: Q1 | B21: Based on TCO, which printer is most cost-effective over 5 years? | C21: Laser (Brother HL-L2350DW) – lower cost per page despite higher upfront cost
A22: Q2 | B22: Would the answer change for a home user printing 5 pages/week? | C22: Yes – inkjet becomes cheaper; low volume doesn't justify laser's upfront cost
A23: Q3 | B23: What non-financial factors should be considered? | C23: Print quality, speed, noise, space, wireless connectivity, brand support
A24: Q4 | B24: What cost components are most significant for a workgroup printer? | C24: Toner/consumables, duty cycle, paper handling capacity, maintenance contracts
A25: Q5 | B25: At what point do both printers break even in cost? | C25: See 3-Year Projection above – crossover typically around Year 2–3 at 750 pg/wk
